{"avatar":"b02b3bd3fc01ceff233e16d35584e389","bracket_id":1041133367858372615,"bracket_overrides_id":null,"company_id":null,"display_order":-9999,"draft_id":"941727080813846528","group_id":null,"last_author_avatar":null,"last_author_display_name":"sys","last_author_id":"166666666666666666","last_author_is_bot":true,"last_message_attachment":null,"last_message_id":"1045635026538008576","last_message_text_map":null,"last_message_time":1703661326587,"last_pinned_message_id":null,"last_read_id":"1045635026538008576","last_transaction_id":null,"league_id":"941727079954006016","loser_bracket_id":1041133367866761219,"loser_bracket_overrides_id":null,"metadata":{"auto_continue":"on","continued":"yes","keeper_deadline":"0","latest_league_winner_roster_id":"3"},"name":"SACK LEAGUE","previous_league_id":null,"roster_positions":["IDP_FLEX","IDP_FLEX","IDP_FLEX","IDP_FLEX","IDP_FLEX","BN","BN","BN"],"scoring_settings":{"blk_kick":0.0,"bonus_sack_2p":1.0,"def_st_ff":0.0,"def_st_fum_rec":0.0,"def_st_td":0.0,"def_td":0.0,"ff":0.0,"fgm_0_19":0.0,"fgm_20_29":0.0,"fgm_30_39":0.0,"fgm_40_49":0.0,"fgm_50p":0.0,"fgmiss":0.0,"fum":0.0,"fum_lost":0.0,"fum_rec":0.0,"fum_rec_td":0.0,"idp_blk_kick":0.0,"idp_def_td":6.0,"idp_ff":1.0,"idp_fum_rec":1.0,"idp_int":0.0,"idp_pass_def":0.0,"idp_qb_hit":1.0,"idp_sack":5.0,"idp_safe":2.0,"idp_tkl_ast":0.0,"idp_tkl_loss":0.0,"idp_tkl_solo":0.0,"int":0.0,"pass_2pt":0.0,"pass_int":0.0,"pass_td":0.0,"pass_yd":0.0,"pts_allow_0":0.0,"pts_allow_14_20":0.0,"pts_allow_1_6":0.0,"pts_allow_21_27":0.0,"pts_allow_28_34":0.0,"pts_allow_35p":0.0,"pts_allow_7_13":0.0,"rec":0.0,"rec_2pt":0.0,"rec_td":0.0,"rec_yd":0.0,"rush_2pt":0.0,"rush_td":0.0,"rush_yd":0.0,"sack":0.0,"safe":0.0,"st_ff":0.0,"st_fum_rec":0.0,"st_td":0.0,"xpm":0.0,"xpmiss":-1.0},"season":"2023","season_type":"regular","settings":{"bench_lock":0,"best_ball":0,"capacity_override":0,"commissioner_direct_invite":0,"daily_waivers":0,"daily_waivers_days":5461,"daily_waivers_hour":0,"daily_waivers_last_ran":6,"disable_adds":0,"disable_trades":0,"draft_rounds":3,"last_report":14,"last_scored_leg":16,"league_average_match":0,"leg":16,"max_keepers":3,"num_teams":10,"offseason_adds":0,"pick_trading":1,"playoff_round_type":0,"playoff_seed_type":0,"playoff_teams":4,"playoff_type":0,"playoff_week_start":15,"reserve_allow_cov":0,"reserve_allow_dnr":1,"reserve_allow_doubtful":0,"reserve_allow_na":0,"reserve_allow_out":1,"reserve_allow_sus":0,"reserve_slots":2,"start_week":1,"taxi_allow_vets":0,"taxi_deadline":0,"taxi_slots":0,"taxi_years":0,"trade_deadline":11,"trade_review_days":0,"type":1,"veto_auto_poll":0,"veto_show_votes":0,"veto_votes_needed":3,"waiver_bid_min":0,"waiver_budget":100,"waiver_clear_days":0,"waiver_day_of_week":2,"waiver_type":1,"was_auto_archived":1},"shard":26,"sport":"nfl","status":"complete","total_rosters":10}