[{"co_owners":null,"keepers":null,"league_id":"916718379451506688","metadata":{"allow_pn_news":"off","allow_pn_scoring":"off","p_nick_10217":"Skoony Tunes","p_nick_1099":"Cheesburger Gut Muhfuckah","p_nick_1266":"3rd Leg Greg","p_nick_1373":"William Turner","p_nick_167":"Tommy Bahama","p_nick_2306":"Uncle Rico","p_nick_2505":"Truth or Darren","p_nick_3164":"Secretariat","p_nick_3198":"The Kraken","p_nick_3199":"Governor Weatherby Swann","p_nick_3214":"Skunter","p_nick_4017":"Blackbeard","p_nick_4033":"Freddie Krueger","p_nick_4068":"Sqwilliam Fancy Pants","p_nick_4098":"Old Yeller","p_nick_4137":"Bootstrap Bill","p_nick_49":"Gabagould","p_nick_4985":"The Trevor Killer \u2620","p_nick_5068":"My wayward son","p_nick_5089":"The","p_nick_5846":"Cap'n Jack Sparrow","p_nick_5849":"Marty","p_nick_5850":"Ex-Gruden Grindr","p_nick_5854":"Chad Kroeger","p_nick_5927":"Elizabeth Swann","p_nick_5980":"\u26fd\ud83e\udd6b","p_nick_5985":"Justin Theoreux","p_nick_6012":"CSCRTMHomerTTPlayoffsWIB","p_nick_6783":"Barbossa","p_nick_6824":"The Jones is for the People","p_nick_6843":"Ocowabunga","p_nick_6850":"Mrs. Garrison","p_nick_6870":"CSTORM Reborn","p_nick_6878":"Tony McCloseSea","p_nick_6945":"Mr. Gibbs Son","p_nick_7002":"Probably getting cut for a kicker","p_nick_7090":"Commodore Norrington","p_nick_7533":"SEC speed ","p_nick_7537":"WFT Cheerleader","p_nick_7547":"Dayman","p_nick_7596":"The Black Pearl","p_nick_7608":"Khalil Slice of Heaven","p_nick_8131":"Bo'sun","p_nick_8135":"Harder and Harder to Breathe","p_nick_8143":"Young William Turner","p_nick_8164":"Golden","p_nick_8205":"Calypso","p_nick_8225":"Ragetti","p_nick_9221":"Mr Gibbs","p_nick_9500":"Fresh Set of","p_nick_9505":"Trevor's Dropped Deuce","p_nick_9753":"Davy Jones","p_nick_BAL":"Charm City Tittie Committee","p_nick_DEN":"The Cavalry","p_nick_MIA":"\ud83d\udc2c Slippy Boiz \ud83d\udc2c","record":"LWLWLLLWLWLWWL","streak":"1L"},"owner_id":"470738199887474688","player_map":null,"players":["10226","10444","10857","1373","4017","4029","4033","4137","5846","5849","5890","5927","6111","6783","6945","7090","7596","8143","8210","9221","9492","9500","9753"],"reserve":["10857","4017"],"roster_id":1,"settings":{"fpts":1641,"fpts_against":1720,"fpts_against_decimal":84,"fpts_decimal":86,"losses":8,"ppts":1928,"ppts_decimal":20,"ties":0,"total_moves":0,"waiver_budget_used":100,"waiver_position":13,"wins":6},"starters":["5849","9221","4137","5846","5927","4033","8143","1373","0","0"],"taxi":null},{"co_owners":null,"keepers":null,"league_id":"916718379451506688","metadata":{"allow_pn_news":"on","allow_pn_scoring":"on","p_nick_1945":"","p_nick_2216":"Salted Caramel Mocha","p_nick_4089":"Gizzard of Oz","p_nick_4666":"Younghoe Boo","p_nick_4892":"","p_nick_4951":"","p_nick_5024":"Beezer Twelve Washingbeard","p_nick_5045":"","p_nick_5850":"Chunk","p_nick_5859":"","p_nick_5870":"","p_nick_616":"Jim","p_nick_6790":"","p_nick_6806":"","p_nick_6814":"","p_nick_7528":"Harry Potter","p_nick_7591":"Doctor Cigarettes","p_nick_7606":"Cadaverous Toblerone","p_nick_PIT":"Steel Cu(m)rtain","p_nick_TB":"Spooky Pirates","record":"LLWWLLWLLLLLLW","streak":"1W"},"owner_id":"616468892608565248","player_map":null,"players":["11199","1945","3214","4080","5045","5848","5850","5859","5870","5872","6845","7562","7571","7591","7600","8111","8134","8139","8147","8160","8230","827","IND"],"reserve":["5848","5870"],"roster_id":2,"settings":{"fpts":1592,"fpts_against":1730,"fpts_against_decimal":2,"fpts_decimal":74,"losses":10,"ppts":1929,"ppts_decimal":98,"ties":0,"total_moves":0,"waiver_budget_used":71,"waiver_position":4,"wins":4},"starters":["7591","8139","8230","5859","5872","7600","7571","827","1945","IND"],"taxi":null},{"co_owners":null,"keepers":null,"league_id":"916718379451506688","metadata":{"p_nick_1234":"Ciara\u2019s little bitch","p_nick_1352":"Trees","p_nick_1689":"","p_nick_3321":"Rapid Dave","p_nick_6011":"Stache","p_nick_6271":"O Face","p_nick_8148":"Rain Man","p_nick_PHI":"The bulldogs","record":"WWWLLWLLLLLLLL","streak":"8L"},"owner_id":"470746994579599360","player_map":null,"players":["10222","10236","1234","1352","4089","5695","5857","6011","650","6824","6828","7066","7588","7670","8121","8148","8168","8205","9229","9757","CHI","PHI"],"reserve":["9229"],"roster_id":3,"settings":{"fpts":1569,"fpts_against":1896,"fpts_against_decimal":60,"fpts_decimal":72,"losses":10,"ppts":1813,"ppts_decimal":14,"ties":0,"total_moves":0,"waiver_budget_used":10,"waiver_position":2,"wins":4},"starters":["1234","7588","8205","1352","8121","10236","8148","6011","650","PHI"],"taxi":null},{"co_owners":null,"keepers":null,"league_id":"916718379451506688","metadata":{"allow_pn_scoring":"on","p_nick_10857":"Hall Monitor","p_nick_10870":"Generic Piss","p_nick_11311":"Jackcum Piss-Browncockgba","p_nick_11533":"Baby Legs","p_nick_1689":"The Milk Missle","p_nick_1848":"Craig","p_nick_2307":"Chris mariota","p_nick_2374":"Chris C (Chris Catch)","p_nick_3164":"Chris F (Chris Fumble)","p_nick_3198":"Chris R (Chris Run)","p_nick_4150":"Gallstones","p_nick_4152":"Chris M","p_nick_4171":"Vincent Smaldone","p_nick_4195":"Ol\u2019 Bucaroo ","p_nick_4571":"Vanilla Viper","p_nick_4973":"Celtic Guardian","p_nick_4981":"Jackcum Piss-Browncockgba","p_nick_5026":"Tre\u2019Cum Smith","p_nick_5086":"Chris M (Chris Marquez Valdes-Scantling)","p_nick_5119":"Chris Kick","p_nick_5844":"Tj Kreem","p_nick_5850":"Black Ranger Bob Biryani","p_nick_5937":"Chris pittsburgh ","p_nick_5967":"Chris Run","p_nick_6234":"Steven","p_nick_6650":"Mike Triangle","p_nick_6789":"Chris Druggs","p_nick_6797":"Dresser Turner-Yeast","p_nick_6803":"Brett Hougendobler","p_nick_6806":"The Running Crooner","p_nick_6819":"Pichael","p_nick_6927":"> leviska shenault (aka old viper)","p_nick_6931":"ChrisJ Dallas","p_nick_6943":"Iceman","p_nick_7002":"L-Kwanjarius Pepperfield","p_nick_7525":"Agave","p_nick_7567":"Useless bitchpussy loser","p_nick_7574":"Dragon","p_nick_7585":"Stairway to Headven","p_nick_7607":"Viper","p_nick_7611":"JuanDamien Nebraska","p_nick_7670":"Anthtonio Brimsticker","p_nick_7891":"Clam Bake","p_nick_8110":"Mike Oxlong","p_nick_8112":"El Tigre","p_nick_8126":"Randy Piss","p_nick_8130":"The Golden Goose","p_nick_8132":"Dozer","p_nick_8151":"Dirty Work","p_nick_8258":"Johnny Cakes","p_nick_8676":"Rico Pube","p_nick_9224":"Mark Walhberg","p_nick_947":"Odool Breakfastham Jr","p_nick_9758":"John Jaguar","p_nick_9998":"Beercock Obama","p_nick_BAL":"Hadrian\u2019s Wall","p_nick_IND":"The Enhanced Fence","p_nick_LAC":"The Phalanx","record":"WWWLLLWLWWWWLL","streak":"2L"},"owner_id":"470739739947823104","player_map":null,"players":["11533","1689","4981","5844","6797","6806","6943","7525","7567","7611","8110","8112","8126","8130","8132","8151","8676","9224","9758","9998","BAL","JAX"],"reserve":["6797","6806"],"roster_id":4,"settings":{"fpts":1820,"fpts_against":1715,"fpts_against_decimal":4,"fpts_decimal":6,"losses":6,"ppts":2201,"ppts_decimal":38,"ties":0,"total_moves":0,"waiver_budget_used":52,"waiver_position":7,"wins":8},"starters":["9758","8151","9224","7525","4981","8110","6943","8112","11533","JAX"],"taxi":null},{"co_owners":null,"keepers":null,"league_id":"916718379451506688","metadata":{"p_nick_1067":"Starvin Marvin","p_nick_10863":"AT Purrry \ud83d\udc08 ","p_nick_1166":"Kirk the Krippled","p_nick_1426":"Steroid Boy","p_nick_1479":"Keenan Kaputt","p_nick_1535":"\ud83d\udc09","p_nick_1737":"Chase Sneezum","p_nick_2133":"Anubis","p_nick_2306":"Dumb Motherfucker","p_nick_2309":"Amari Pooper","p_nick_2320":"","p_nick_2391":"Stump","p_nick_3161":"Captain Retard","p_nick_3225":"Turnip Boy","p_nick_3969":"Lenny Forknight","p_nick_4029":"Old Yeller","p_nick_4131":"Boy in the Crevasse","p_nick_4144":"Biryani Bill","p_nick_4177":"Snack Hollins","p_nick_4179":"Rocket Man \ud83d\ude80 ","p_nick_4381":"\ud83c\udf51 Tight End Tays-Yum \ud83c\udf51  ","p_nick_4454":"Bourne the Busted","p_nick_4622":"","p_nick_4663":"Mouse Cop","p_nick_4951":"Aka DJ Chark","p_nick_4973":"Gayden Gerst","p_nick_4984":"King Ragnar","p_nick_5012":"Mark the Mangled","p_nick_5284":"Viper","p_nick_5947":"Serpent","p_nick_5970":"Stan Darsh","p_nick_5987":"Alex the Absent","p_nick_642":"Golden Taint","p_nick_6804":"Johnny Dickshot","p_nick_6870":"CSTORM","p_nick_6951":"Peen-o Benjamin","p_nick_6955":"The Warthog","p_nick_7045":"Todd Tandoori","p_nick_7547":"Amon-Ra St. Brown","p_nick_7551":"Flash (sucks)","p_nick_7571":"Rico Front Busi","p_nick_7593":"FumbleBust","p_nick_8131":"Or Isaiah Unlikely?","p_nick_8138":"Diablo","p_nick_8154":"Lazarus","p_nick_8195":"Ronnie the Rat \ud83d\udc00 ","p_nick_947":"Jamstring Hulio","p_nick_9505":"Bean","p_nick_956":"Stump","p_nick_96":"Cunt","p_nick_GB":"The Green Bae Crackers","p_nick_WAS":"The Redskins","record":"WWWWWWWWWWWWWW","streak":"14W"},"owner_id":"470754140222386176","player_map":null,"players":["10863","1166","1426","1479","19","2133","2216","3198","4179","4454","4663","4984","5012","5947","5987","6083","6136","7021","8131","8138","8195","9505","KC"],"reserve":["1166","5012"],"roster_id":5,"settings":{"fpts":2067,"fpts_against":1506,"fpts_against_decimal":82,"fpts_decimal":8,"losses":0,"ppts":2357,"ppts_decimal":52,"ties":0,"total_moves":0,"waiver_budget_used":95,"waiver_position":8,"wins":14},"starters":["19","8138","4663","2133","2216","8131","1426","4984","6083","KC"],"taxi":null},{"co_owners":null,"keepers":null,"league_id":"916718379451506688","metadata":{"allow_pn_news":"off","allow_pn_scoring":"on","p_nick_1479":"Cummin Allen","p_nick_3161":"The Four Fingered Wonder","p_nick_3664":"JD McCocksuck","p_nick_4034":"Chris M","p_nick_4037":"The amazing ball catcher guy","p_nick_4217":"Boagrius","p_nick_4273":"Garth Garthson","p_nick_4435":"Tony Frisker","p_nick_4943":"Mononucleosis Apotheosis","p_nick_5185":"","p_nick_5916":"The Last Horcrux","p_nick_5937":"Nikephorus Johnson","p_nick_6156":"Citrus bowl guy","p_nick_6770":"Joseph Quinctius Cincinnatus","p_nick_6805":"Kum Jam Slamler","p_nick_7042":"","p_nick_7593":"Trey Sercum(cision?)","p_nick_8118":"Country Club Menace","p_nick_8146":"Kirkland Lawrence Cager","p_nick_9222":"Bucephalus","p_nick_9228":"Lisan al Gaib","p_nick_96":"Asimptoematic","p_nick_PIT":"Theodosian Wall","record":"LLLLLLLWLLWLLL","streak":"3L"},"owner_id":"470761942894505984","player_map":null,"players":["10229","1067","11256","1535","4037","4111","4217","5185","5916","5937","6770","6805","7042","8118","8146","8188","8221","9222","9228","9481","9508","PIT"],"reserve":["6770","9481"],"roster_id":6,"settings":{"fpts":1464,"fpts_against":1842,"fpts_against_decimal":8,"fpts_decimal":52,"losses":12,"ppts":1592,"ppts_decimal":22,"ties":0,"total_moves":0,"waiver_budget_used":10,"waiver_position":10,"wins":2},"starters":["9228","9508","4111","10229","4037","4217","8146","5937","7042","PIT"],"taxi":null},{"co_owners":null,"keepers":null,"league_id":"916718379451506688","metadata":{"p_nick_10232":"Mr Big Shot","p_nick_10444":"The perfect combination of cute and sexy","p_nick_11439":"Jackal","p_nick_138":"is NOT in the best shape of his life","p_nick_1386":"Pasta Fazool","p_nick_1426":"Gary Bopkins","p_nick_2152":"Mr. Biggles","p_nick_2251":"Captain Cappuccino","p_nick_2378":"Kevin Coleman","p_nick_2583":"WR1","p_nick_3161":"Bubble Boy","p_nick_3164":"Bird Man","p_nick_3200":"\u00a3","p_nick_391":"is content. ","p_nick_3976":"Mitch Pins","p_nick_4147":"Smoochie Perine","p_nick_4219":"Sleeping Giant","p_nick_5045":"Sourtland Button","p_nick_5121":"\u2018Ello Poppet","p_nick_5859":"Ada\u2019arious Jumblebee Brown","p_nick_5967":"BMJR","p_nick_5970":"Stan Darsh","p_nick_5980":"The Magic Man","p_nick_6011":"Johnny Dogs","p_nick_6694":"The Process","p_nick_6768":"Bubba","p_nick_7538":"Four-Pick Slick","p_nick_7547":"Sun Gawd","p_nick_7551":"Flash","p_nick_7553":"Pitters","p_nick_7572":"is Single. ","p_nick_7574":"\u201cYou\u2019ll never get this\u201d","p_nick_7596":"Double Meat","p_nick_7670":"Deedee Megadoodoo","p_nick_7794":"Chris E","p_nick_8135":"BARKS","p_nick_8136":"St. Elmo\u2019s Fire","p_nick_8153":"Chonkers","p_nick_8155":"Phantom","p_nick_8157":"ZADDE","p_nick_8162":"Sammy 6 Cups \u2615\ufe0f","p_nick_8167":"Gazelle","p_nick_8168":"Great film","p_nick_8171":"","p_nick_8210":"","p_nick_8223":"The Ageless Wonder","p_nick_9220":"Evan Dyll","p_nick_9227":"Izzzy Anaconda","p_nick_9501":"Poppa Doc","p_nick_9509":"Venom","p_nick_954":"He\u2019s (definitely not) back!","p_nick_9999":"Duke\u2019s Mayo Bowl","p_nick_DEN":"Buckin\u2019","record":"WLWLWWLLWWWWWL","streak":"1L"},"owner_id":"470767876421185536","player_map":null,"players":["10232","3225","3257","4098","4147","4985","6768","7547","7553","7606","8135","8136","8155","8162","8167","9220","9227","9490","9501","9506","9509","9999"],"reserve":["9220"],"roster_id":7,"settings":{"fpts":1785,"fpts_against":1635,"fpts_against_decimal":94,"fpts_decimal":66,"losses":5,"ppts":1945,"ppts_decimal":76,"ties":0,"total_moves":0,"waiver_budget_used":90,"waiver_position":12,"wins":9},"starters":["6768","8136","9509","7547","9501","7553","8155","8162","0","0"],"taxi":null},{"co_owners":null,"keepers":null,"league_id":"916718379451506688","metadata":{"record":"LLWLWLWLLWLWLL","streak":"2L"},"owner_id":"471013131812859904","player_map":null,"players":["10235","2309","2319","3163","3271","4040","421","4666","4983","5000","5022","5046","5119","6151","6801","7601","7608","8129","8159","9488","SF"],"reserve":null,"roster_id":8,"settings":{"fpts":1472,"fpts_against":1628,"fpts_against_decimal":90,"fpts_decimal":38,"losses":9,"ppts":1669,"ppts_decimal":56,"ties":0,"total_moves":0,"waiver_budget_used":22,"waiver_position":3,"wins":5},"starters":["3163","10235","7608","6801","9488","5022","4983","421","5119","SF"],"taxi":null},{"co_owners":null,"keepers":null,"league_id":"916718379451506688","metadata":{"p_nick_10219":"C(um)-Rod","p_nick_10222":"The Western Michiganman","p_nick_11306":"","p_nick_1386":"Mixons Pocket Pussy","p_nick_1837":"Jimmy Heaters","p_nick_1992":"Cassian","p_nick_2749":"Mr. No Knees","p_nick_3163":"Donald Dunn","p_nick_3198":"Tennesee Locomotive","p_nick_3199":"(Get off my) Lawn boy ","p_nick_3209":"Saquons Drink Holder","p_nick_4054":"Return of the MAC","p_nick_4149":"Pikachu","p_nick_4227":"Harry B","p_nick_4866":"Smash Williams ","p_nick_4985":"Ken Walker Sr.","p_nick_4993":"Jax Teller","p_nick_5038":"The Concierge","p_nick_5121":"Handsome CMC","p_nick_5133":"Bobby Munson","p_nick_5870":"Greenrock Dollar Beers ","p_nick_6074":"Cuntiferius Rex ","p_nick_6659":"Creamy Craig","p_nick_6794":"Mr Wick","p_nick_6813":"Minshews Wintergreen Long Cut","p_nick_6828":"Algiers Jameal William","p_nick_6853":"Puka\u2019s Pocket Puss ","p_nick_6904":"Vince Howard ","p_nick_7526":"2 Fast 2 Furious","p_nick_7538":"The Provo Pounder","p_nick_7608":"Herbert #1","p_nick_8140":"Caine","p_nick_8145":"King of Long Island","p_nick_8183":"Mike Winchell","p_nick_9754":"The Bowery King","p_nick_BUF":"Professor McDermotts Math Class","record":"LWWWWWWLLLWLWW","streak":"2W"},"owner_id":"472885207335170048","player_map":null,"players":["10219","2749","3199","3321","3969","4149","4227","4866","4972","5038","5133","5284","5374","6794","6813","6904","7526","7538","8140","8183","9487","9754","BUF"],"reserve":["10219","3199"],"roster_id":9,"settings":{"fpts":1946,"fpts_against":1767,"fpts_against_decimal":22,"fpts_decimal":20,"losses":5,"ppts":2126,"ppts_decimal":54,"ties":0,"total_moves":0,"waiver_budget_used":95,"waiver_position":11,"wins":9},"starters":["6904","6813","4866","3321","6794","5133","9754","8183","4227","BUF"],"taxi":null},{"co_owners":null,"keepers":null,"league_id":"916718379451506688","metadata":{"allow_pn_scoring":"on","p_nick_1049":"The HSman","p_nick_10859":"Vance Bordeaux","p_nick_10866":"Desperado","p_nick_1264":"Steve-O","p_nick_1408":"Le\u2019Cum","p_nick_2078":"Shadowmaster","p_nick_2216":"Big Splendor ","p_nick_2309":"Sideburnz","p_nick_2374":"Sabertooth","p_nick_2449":"Eclipse","p_nick_2711":"Tight Heinie","p_nick_3271":"Kyle Joseph Mansour","p_nick_3294":"Dakota Sins","p_nick_4149":"Jaws","p_nick_4197":"Muscle Hamster ","p_nick_4198":"Agamemnon","p_nick_4455":"Rider-level acquisition ","p_nick_4741":"Chaka D(h)an","p_nick_4973":"Gaylord Gurst","p_nick_4985":"Hibiscus ","p_nick_5133":"Conch","p_nick_5284":"J1zzy RB1","p_nick_536":"CSAB","p_nick_5872":"Big Cum","p_nick_5890":"City Slicka","p_nick_5967":"Starflower","p_nick_5980":"Myles Fart","p_nick_6074":"Malibu","p_nick_6148":"The Thin Pistol","p_nick_6789":"9 Ropez","p_nick_6790":"Pegasus","p_nick_6803":"Akhal-Teke","p_nick_6806":"Sultan","p_nick_6814":"Viper","p_nick_6819":"Storm Titan ","p_nick_6826":"Larry Thunderhog","p_nick_6845":"Snackary Piss","p_nick_6849":"Denzel Drop","p_nick_6853":"Tummy Stix","p_nick_6857":"Johnson 1","p_nick_6869":"Son of the Seas","p_nick_6885":"Lead Dog","p_nick_6906":"Golden Pandy","p_nick_6938":"Roach","p_nick_6951":"Rio","p_nick_6960":"Johnson 2","p_nick_6984":"Tony Bananas","p_nick_7064":"Charles de Batz de Castlemore","p_nick_7523":"Gunther Eagleman","p_nick_7540":"Randall Cobb","p_nick_7561":"Knuckles ","p_nick_7564":"Hidalgo ","p_nick_7565":"State Trooper","p_nick_7568":"The Mystery Machine","p_nick_7571":"Shoddy Business","p_nick_7599":"Chongus","p_nick_7600":"Mr. New Bootie","p_nick_7610":"Junior Varsity 69","p_nick_7670":"Beach Bum","p_nick_7703":"The Argonaut","p_nick_7828":"Notah Begay III","p_nick_8136":"Meus Susurrar","p_nick_8142":"Billy Hoyle","p_nick_8150":"Dick Tucker","p_nick_8167":"Mr. 63","p_nick_8168":"Cyclone","p_nick_8172":"Chupacabra ","p_nick_8189":"Usurper ","p_nick_8208":"Lucas","p_nick_8228":"Pinto Bean","p_nick_9225":"Axel Midnight ","p_nick_9226":"Caballero","p_nick_9484":"Gruyere","p_nick_9486":"Big Wicks","p_nick_9492":"Tres Commas","p_nick_9494":"MangoMan","p_nick_96":"Twat the Cursed","p_nick_ARI":"Sultans","p_nick_BUF":"Garth Ruffalo\u2019s Buffalos","p_nick_PIT":"My Strong Boys","p_nick_WAS":"Washington Football Cream Team","record":"LLLWWWLWWLWWWW","restrict_pn_scoring_starters_only":"on","streak":"4W"},"owner_id":"472893697663430656","player_map":null,"players":["10859","10866","11439","1264","2251","2374","2449","3294","5967","6790","6803","7523","7564","7610","8117","8172","8228","9225","9226","9484","9486","9494","CLE"],"reserve":["7523","8172"],"roster_id":10,"settings":{"fpts":1978,"fpts_against":1738,"fpts_against_decimal":96,"fpts_decimal":18,"losses":5,"ppts":2289,"ppts_decimal":78,"ties":0,"total_moves":0,"waiver_budget_used":100,"waiver_position":9,"wins":9},"starters":["3294","5967","9226","2449","6803","10859","6790","7564","1264","CLE"],"taxi":null},{"co_owners":["883092641720721408"],"keepers":null,"league_id":"916718379451506688","metadata":{"p_nick_10225":"Django","p_nick_1166":"Carson Wentz","p_nick_1348":"The Real DHop","p_nick_1379":"PAWG","p_nick_1433":"Denver RB1","p_nick_1466":"Troy Bolton","p_nick_2078":"LSU #1 Booster","p_nick_2505":"Aaron Hernandez Jr","p_nick_2549":"Semen Demon","p_nick_3202":"Poopity Scoop","p_nick_3969":"Larry Hoover","p_nick_4018":"Coconut Corn Husky","p_nick_4034":"Blue-Eyes White Dragon","p_nick_4055":"Juice","p_nick_4068":"Bricksquad ","p_nick_4881":"Cum Runner","p_nick_4892":"Cigarette Enjoyer","p_nick_4950":"Not a JAG","p_nick_4981":"Pete Rose","p_nick_5880":"Thick n Creamy","p_nick_5995":"","p_nick_6074":"Cheeseburger Eddie","p_nick_6938":"Cum Ankles","p_nick_7002":"Dom of the Year","p_nick_7543":"Petey Jones","p_nick_7561":"Steve Balboni","p_nick_8117":"First-Team Practice Squad","p_nick_8137":"NBA YoungBoy","p_nick_8146":"Private Ryan","p_nick_8154":"Curtis James Jackson III","p_nick_8160":"The Allegheny Cum Slinger","p_nick_8161":"Reek","p_nick_8259":"Dickher","p_nick_9493":"Pook Nukem","p_nick_9502":"Larry Lonestar","p_nick_9508":"Phalanx","p_nick_9511":"Big Meech","p_nick_9756":"Ace Ventura","p_nick_DEN":"Lets Ride","p_nick_NYJ":"Sauce on a Plane \ud83d\udee9\ufe0f","record":"WWLWWLWWLWWWWW","streak":"5W"},"owner_id":"472894142150602752","player_map":null,"players":["10225","1466","2505","3286","4018","4034","4068","4881","4892","4950","7002","7543","7561","8137","8154","8259","9493","9502","9511","9756","DEN","LV","NYJ"],"reserve":["4068","9502"],"roster_id":11,"settings":{"fpts":1949,"fpts_against":1714,"fpts_against_decimal":82,"fpts_decimal":10,"losses":3,"ppts":2301,"ppts_decimal":70,"ties":0,"total_moves":0,"waiver_budget_used":100,"waiver_position":14,"wins":11},"starters":["4881","4034","7543","9493","8137","1466","4018","4892","8259","LV"],"taxi":null},{"co_owners":null,"keepers":null,"league_id":"916718379451506688","metadata":{"p_nick_10223":"Devy Boi prototype","p_nick_167":"Mithrandir ","p_nick_1825":"Kirkland OBJ","p_nick_1837":"Jonny Sins ","p_nick_3294":"QB1","p_nick_391":"The Glizzy Gobbler","p_nick_3969":"Playoff Lenny","p_nick_4017":"Andrew Cuomo","p_nick_4035":"Hogfather CUMara","p_nick_4066":"Hubert Cumberdale","p_nick_4082":"Hambone ","p_nick_4150":"Kirkland Saquon","p_nick_4179":"Arbiter, Halo 2","p_nick_4195":"Delco Deloitte Associate","p_nick_5001":"Augustus Gloop","p_nick_5122":"Eric Adams ","p_nick_5199":"Bryan Carse ","p_nick_5248":"The Liberian Locomotive","p_nick_5917":"Morning Wood","p_nick_5967":"Kirkland Zeke","p_nick_5995":"D'Angelo Barksdale","p_nick_6130":"One-Trick Pony","p_nick_6798":"JJAW","p_nick_6819":"Rex Foreman","p_nick_6869":"The hebrew fisherman ","p_nick_6886":"Cunt","p_nick_6931":"Mr Irrelevant","p_nick_7594":"Secretariat","p_nick_8144":"Castilian Suave ","p_nick_928":"Donald Driver and Greg Jennings ass baby ","p_nick_9497":"Park Ave Burner","p_nick_96":"Burning Man","p_nick_9997":"Snapdragon","p_nick_BUF":"The wagons ","p_nick_DAL":"Dem Franchize Boyz","record":"WWLLLWWWWWLLWW","streak":"2W"},"owner_id":"472895518431768576","player_map":null,"players":["10223","10983","1837","4035","4066","4082","4195","4381","5001","5248","5995","6130","6804","6819","7594","8144","9231","9497","96","9997","DAL","HOU"],"reserve":["96"],"roster_id":12,"settings":{"fpts":1882,"fpts_against":1695,"fpts_against_decimal":58,"fpts_decimal":42,"losses":5,"ppts":2131,"ppts_decimal":74,"ties":0,"total_moves":0,"waiver_budget_used":100,"waiver_position":5,"wins":9},"starters":["6804","4035","7594","9997","4082","4066","5248","6130","4195","HOU"],"taxi":null},{"co_owners":null,"keepers":null,"league_id":"916718379451506688","metadata":{"allow_pn_news":"on","allow_pn_scoring":"on","record":"LLLLWWLLWLLLLW","streak":"1W"},"owner_id":"472972716996030464","player_map":null,"players":["10871","1339","1476","2078","2161","2197","4039","4046","4171","4234","4988","5086","5409","5892","5906","5955","6421","6694","6786","7839","9482","LAR"],"reserve":["4988"],"roster_id":13,"settings":{"fpts":1500,"fpts_against":1704,"fpts_against_decimal":60,"fpts_decimal":76,"losses":10,"ppts":1750,"ppts_decimal":34,"ties":0,"total_moves":0,"waiver_budget_used":82,"waiver_position":6,"wins":4},"starters":["4046","5892","1476","4039","6786","5409","2078","2197","7839","LAR"],"taxi":null},{"co_owners":null,"keepers":null,"league_id":"916718379451506688","metadata":{"p_nick_3164":"Chonk Norris","p_nick_5848":"Fenway DiNardo","p_nick_5985":"Moreau deez \ud83e\udd5c ","p_nick_6826":"Larry Beefdong","p_nick_7527":"McGangbang Jones","record":"WLLWLLLWWLLLLL","streak":"5L"},"owner_id":"868283597898031104","player_map":null,"players":["10937","2028","3161","3164","4199","5052","5985","6820","6826","7527","7528","7569","7605","7607","8119","8142","8150","8157","8253","LAC","SEA"],"reserve":null,"roster_id":14,"settings":{"fpts":1353,"fpts_against":1727,"fpts_against_decimal":20,"fpts_decimal":94,"losses":10,"ppts":1619,"ppts_decimal":40,"ties":0,"total_moves":0,"waiver_budget_used":0,"waiver_position":1,"wins":4},"starters":["2028","3164","7528","8119","8253","6826","8142","6820","10937","LAC"],"taxi":null}]