{"fantasy_content": {"xml:lang": "en-US", "yahoo:uri": "/fantasy/v2/league/406.l.60044", "league": [{"league_key": "406.l.60044", "league_id": "60044", "name": "moneyleague", "url": "https://football.fantasysports.yahoo.com/2021/f1/60044", "recordbook_url": "https://football.fantasysports.yahoo.com/2021/f1/60044/recordbook?layout=webview&device=smartphone", "logo_url": false, "password": "", "draft_status": "postdraft", "num_teams": 12, "edit_key": "17", "weekly_deadline": "", "roster_type": "week", "league_update_timestamp": "1642059268", "scoring_type": "head", "scoring_label": "H2H", "league_type": "private", "renew": "399_64590", "renewed": "414_591940", "felo_tier": "silver", "is_highscore": false, "is_guillotine": "0", "matchup_week": 17, "iris_group_chat_id": "", "short_invitation_url": "https://football.fantasysports.yahoo.com/2021/f1/60044/invitation?key=7d31aefa49c205a9&ikey=461d52c9f8fad735", "allow_add_to_dl_extra_pos": 1, "is_pro_league": "0", "is_cash_league": "0", "current_week": "17", "start_week": "1", "start_date": "2021-09-09", "end_week": "17", "end_date": "2022-01-03", "is_finished": 1, "is_plus_league": "0", "game_code": "nfl", "season": "2021"}], "time": "26.116847991943ms", "copyright": "Certain Data by Sportradar, Stats Perform and Rotowire", "refresh_rate": "30"}}