{"fantasy_content": {"xml:lang": "en-US", "yahoo:uri": "/fantasy/v2/league/380.l.209074/standings", "league": [{"league_key": "380.l.209074", "league_id": "209074", "name": "Playoffs???????", "url": "https://football.fantasysports.yahoo.com/2018/f1/209074", "recordbook_url": "https://football.fantasysports.yahoo.com/2018/f1/209074/recordbook?layout=webview&device=smartphone", "logo_url": false, "draft_status": "postdraft", "num_teams": 14, "edit_key": "16", "weekly_deadline": "", "roster_type": "week", "league_update_timestamp": "1546500685", "scoring_type": "head", "scoring_label": "H2H", "league_type": "private", "renew": "371_518793", "renewed": "390_42535", "felo_tier": "silver", "is_highscore": false, "is_guillotine": "0", "matchup_week": 16, "iris_group_chat_id": "", "allow_add_to_dl_extra_pos": 0, "is_pro_league": "0", "is_cash_league": "0", "current_week": "16", "start_week": "1", "start_date": "2018-09-06", "end_week": "16", "end_date": "2018-12-24", "is_finished": 1, "is_plus_league": "0", "game_code": "nfl", "season": "2018"}, {"standings": [{"teams": {"0": {"team": [[{"team_key": "380.l.209074.t.1"}, {"team_id": "1"}, {"name": "Always Rosterbating"}, [], {"url": "https://football.fantasysports.yahoo.com/2018/f1/209074/1"}, {"team_logos": [{"team_logo": {"size": "large", "url": "https://yahoofantasysports-res.cloudinary.com/image/upload/t_s192sq/fantasy-logos/44266171362_490048.jpg"}}]}, {"previous_season_team_rank": 2}, [], {"waiver_priority": 4}, {"faab_balance": "0"}, {"number_of_moves": 36}, {"number_of_trades": "2"}, {"roster_adds": {"coverage_type": "week", "coverage_value": 17, "value": "0"}}, {"clinched_playoffs": 1}, {"league_scoring_type": "head"}, [], [], {"has_draft_grade": 1, "draft_grade": "B", "draft_recap_url": "https://football.fantasysports.yahoo.com/2018/f1/209074/1/draftrecap"}, [], [], [], [], [], {"managers": [{"manager": {"manager_id": "1", "nickname": "Dave", "guid": "--hidden--", "is_commissioner": "1", "image_url": "https://s.yimg.com/ag/images/default_user_profile_pic_64sq.jpg", "felo_score": "926", "felo_tier": "diamond"}}]}], {"team_points": {"coverage_type": "season", "season": "2018", "total": "1425.22"}}, {"team_standings": {"rank": 1, "playoff_seed": "1", "outcome_totals": {"wins": "12", "losses": "1", "ties": 0, "percentage": ".923"}, "streak": {"type": "win", "value": "12"}, "points_for": "1425.22", "points_against": 1147.3800000000003}}]}, "1": {"team": [[{"team_key": "380.l.209074.t.12"}, {"team_id": "12"}, {"name": "Taco Taco"}, [], {"url": "https://football.fantasysports.yahoo.com/2018/f1/209074/12"}, {"team_logos": [{"team_logo": {"size": "large", "url": "https://s.yimg.com/cv/apiv2/default/nfl/nfl_11.png"}}]}, {"previous_season_team_rank": 3}, [], {"waiver_priority": 13}, {"faab_balance": "5"}, {"number_of_moves": 25}, {"number_of_trades": "2"}, {"roster_adds": {"coverage_type": "week", "coverage_value": 17, "value": "0"}}, {"clinched_playoffs": 1}, {"league_scoring_type": "head"}, [], [], {"has_draft_grade": 1, "draft_grade": "C", "draft_recap_url": "https://football.fantasysports.yahoo.com/2018/f1/209074/12/draftrecap"}, [], [], [], [], [], {"managers": [{"manager": {"manager_id": "12", "nickname": "-- hidden --", "guid": "--hidden--", "image_url": "https://s.yimg.com/ag/images/default_user_profile_pic_64sq.jpg", "felo_score": "732", "felo_tier": "gold"}}]}], {"team_points": {"coverage_type": "season", "season": "2018", "total": "1264.68"}}, {"team_standings": {"rank": 2, "playoff_seed": "3", "outcome_totals": {"wins": "9", "losses": "4", "ties": 0, "percentage": ".692"}, "streak": {"type": "win", "value": "2"}, "points_for": "1264.68", "points_against": 1257.44}}]}, "2": {"team": [[{"team_key": "380.l.209074.t.10"}, {"team_id": "10"}, {"name": "Ozmataz Buckshank"}, [], {"url": "https://football.fantasysports.yahoo.com/2018/f1/209074/10"}, {"team_logos": [{"team_logo": {"size": "large", "url": "https://s.yimg.com/cv/apiv2/default/nfl/nfl_8.png"}}]}, {"previous_season_team_rank": 7}, [], {"waiver_priority": 3}, {"faab_balance": "5"}, {"number_of_moves": 11}, {"number_of_trades": 0}, {"roster_adds": {"coverage_type": "week", "coverage_value": 17, "value": "0"}}, {"clinched_playoffs": 1}, {"league_scoring_type": "head"}, [], [], {"has_draft_grade": 1, "draft_grade": "B", "draft_recap_url": "https://football.fantasysports.yahoo.com/2018/f1/209074/10/draftrecap"}, [], [], [], [], [], {"managers": [{"manager": {"manager_id": "10", "nickname": "Kevin Muldoon", "guid": "--hidden--", "image_url": "https://s.yimg.com/ag/images/4588/38321673505_a3c7ab_64sq.jpg", "felo_score": "584", "felo_tier": "bronze"}}]}], {"team_points": {"coverage_type": "season", "season": "2018", "total": "1333.28"}}, {"team_standings": {"rank": 3, "playoff_seed": "4", "outcome_totals": {"wins": "8", "losses": "5", "ties": 0, "percentage": ".615"}, "streak": {"type": "loss", "value": "1"}, "points_for": "1333.28", "points_against": 1161.7399999999998}}]}, "3": {"team": [[{"team_key": "380.l.209074.t.5"}, {"team_id": "5"}, {"name": "Hasselhoffies"}, [], {"url": "https://football.fantasysports.yahoo.com/2018/f1/209074/5"}, {"team_logos": [{"team_logo": {"size": "large", "url": "https://yahoofantasysports-res.cloudinary.com/image/upload/t_s192sq/fantasy-logos/25342649015_97dc1346cd.jpg"}}]}, {"previous_season_team_rank": 11}, [], {"waiver_priority": 2}, {"faab_balance": "59"}, {"number_of_moves": 5}, {"number_of_trades": 0}, {"roster_adds": {"coverage_type": "week", "coverage_value": 17, "value": "0"}}, {"clinched_playoffs": 1}, {"league_scoring_type": "head"}, [], [], {"has_draft_grade": 1, "draft_grade": "C", "draft_recap_url": "https://football.fantasysports.yahoo.com/2018/f1/209074/5/draftrecap"}, [], [], [], [], [], {"managers": [{"manager": {"manager_id": "5", "nickname": "Mike", "guid": "--hidden--", "image_url": "https://s.yimg.com/ag/images/default_user_profile_pic_64sq.jpg", "felo_score": "743", "felo_tier": "gold"}}]}], {"team_points": {"coverage_type": "season", "season": "2018", "total": "1398.10"}}, {"team_standings": {"rank": 4, "playoff_seed": "2", "outcome_totals": {"wins": "10", "losses": "3", "ties": 0, "percentage": ".769"}, "streak": {"type": "win", "value": "4"}, "points_for": "1398.10", "points_against": 1204.3600000000001}}]}, "4": {"team": [[{"team_key": "380.l.209074.t.2"}, {"team_id": "2"}, {"name": "Beats By Ray"}, [], {"url": "https://football.fantasysports.yahoo.com/2018/f1/209074/2"}, {"team_logos": [{"team_logo": {"size": "large", "url": "https://yahoofantasysports-res.cloudinary.com/image/upload/t_s192sq/fantasy-logos/25246750471_dcb590e72a.jpg"}}]}, {"previous_season_team_rank": 8}, [], {"waiver_priority": 12}, {"faab_balance": "34"}, {"number_of_moves": 15}, {"number_of_trades": "2"}, {"roster_adds": {"coverage_type": "week", "coverage_value": 17, "value": "0"}}, {"clinched_playoffs": 1}, {"league_scoring_type": "head"}, [], [], {"has_draft_grade": 1, "draft_grade": "A-", "draft_recap_url": "https://football.fantasysports.yahoo.com/2018/f1/209074/2/draftrecap"}, [], [], [], [], [], {"managers": [{"manager": {"manager_id": "2", "nickname": "Jeremy", "guid": "--hidden--", "image_url": "https://s.yimg.com/ag/images/4593/27433869669_ce684b_64sq.jpg", "felo_score": "771", "felo_tier": "gold"}}]}], {"team_points": {"coverage_type": "season", "season": "2018", "total": "1151.98"}}, {"team_standings": {"rank": 5, "playoff_seed": "5", "outcome_totals": {"wins": "8", "losses": "5", "ties": 0, "percentage": ".615"}, "streak": {"type": "loss", "value": "2"}, "points_for": "1151.98", "points_against": 1022.26}}]}, "5": {"team": [[{"team_key": "380.l.209074.t.3"}, {"team_id": "3"}, {"name": "Narcos"}, [], {"url": "https://football.fantasysports.yahoo.com/2018/f1/209074/3"}, {"team_logos": [{"team_logo": {"size": "large", "url": "https://yahoofantasysports-res.cloudinary.com/image/upload/t_s192sq/fantasy-logos/43618691554_2243cb.jpg"}}]}, {"previous_season_team_rank": 5}, [], {"waiver_priority": 5}, {"faab_balance": "0"}, {"number_of_moves": 26}, {"number_of_trades": 0}, {"roster_adds": {"coverage_type": "week", "coverage_value": 17, "value": "0"}}, {"clinched_playoffs": 1}, {"league_scoring_type": "head"}, [], [], {"has_draft_grade": 1, "draft_grade": "C", "draft_recap_url": "https://football.fantasysports.yahoo.com/2018/f1/209074/3/draftrecap"}, [], [], [], [], [], {"managers": [{"manager": {"manager_id": "3", "nickname": "Juan", "guid": "--hidden--", "image_url": "https://s.yimg.com/ag/images/default_user_profile_pic_64sq.jpg", "felo_score": "591", "felo_tier": "bronze"}}]}], {"team_points": {"coverage_type": "season", "season": "2018", "total": "1331.62"}}, {"team_standings": {"rank": 6, "playoff_seed": "6", "outcome_totals": {"wins": "7", "losses": "6", "ties": 0, "percentage": ".538"}, "streak": {"type": "loss", "value": "1"}, "points_for": "1331.62", "points_against": 1293.16}}]}, "6": {"team": [[{"team_key": "380.l.209074.t.13"}, {"team_id": "13"}, {"name": "Washington Redskins"}, [], {"url": "https://football.fantasysports.yahoo.com/2018/f1/209074/13"}, {"team_logos": [{"team_logo": {"size": "large", "url": "https://yahoofantasysports-res.cloudinary.com/image/upload/t_s192sq/fantasy-logos/28917190744_1cc2190a09.jpg"}}]}, {"previous_season_team_rank": 13}, [], {"waiver_priority": 9}, {"faab_balance": "50"}, {"number_of_moves": 9}, {"number_of_trades": "1"}, {"roster_adds": {"coverage_type": "week", "coverage_value": 17, "value": "0"}}, [], {"league_scoring_type": "head"}, [], [], {"has_draft_grade": 1, "draft_grade": "C", "draft_recap_url": "https://football.fantasysports.yahoo.com/2018/f1/209074/13/draftrecap"}, [], [], [], [], [], {"managers": [{"manager": {"manager_id": "13", "nickname": "Kyle", "guid": "--hidden--", "image_url": "https://s.yimg.com/ag/images/default_user_profile_pic_64sq.jpg", "felo_score": "638", "felo_tier": "silver"}}]}], {"team_points": {"coverage_type": "season", "season": "2018", "total": "1190.58"}}, {"team_standings": {"rank": 7, "playoff_seed": "8", "outcome_totals": {"wins": "7", "losses": "6", "ties": 0, "percentage": ".538"}, "streak": {"type": "win", "value": "1"}, "points_for": "1190.58", "points_against": 1178.1000000000001}}]}, "7": {"team": [[{"team_key": "380.l.209074.t.9"}, {"team_id": "9"}, {"name": "This One's for Gore"}, [], {"url": "https://football.fantasysports.yahoo.com/2018/f1/209074/9"}, {"team_logos": [{"team_logo": {"size": "large", "url": "https://s.yimg.com/cv/apiv2/default/nfl/nfl_10.png"}}]}, {"previous_season_team_rank": 9}, [], {"waiver_priority": 6}, {"faab_balance": "0"}, {"number_of_moves": 31}, {"number_of_trades": "1"}, {"roster_adds": {"coverage_type": "week", "coverage_value": 17, "value": "0"}}, [], {"league_scoring_type": "head"}, [], [], {"has_draft_grade": 1, "draft_grade": "B+", "draft_recap_url": "https://football.fantasysports.yahoo.com/2018/f1/209074/9/draftrecap"}, [], [], [], [], [], {"managers": [{"manager": {"manager_id": "9", "nickname": "Troy", "guid": "--hidden--", "image_url": "https://s.yimg.com/ag/images/default_user_profile_pic_64sq.jpg", "felo_score": "663", "felo_tier": "silver"}}]}], {"team_points": {"coverage_type": "season", "season": "2018", "total": "1315.72"}}, {"team_standings": {"rank": 8, "playoff_seed": "7", "outcome_totals": {"wins": "7", "losses": "6", "ties": 0, "percentage": ".538"}, "streak": {"type": "win", "value": "1"}, "points_for": "1315.72", "points_against": 1259.48}}]}, "8": {"team": [[{"team_key": "380.l.209074.t.4"}, {"team_id": "4"}, {"name": "Cinderella Story"}, [], {"url": "https://football.fantasysports.yahoo.com/2018/f1/209074/4"}, {"team_logos": [{"team_logo": {"size": "large", "url": "https://yahoofantasysports-res.cloudinary.com/image/upload/t_s192sq/fantasy-logos/36725865932_5fcda6.jpg"}}]}, {"previous_season_team_rank": 10}, [], {"waiver_priority": 14}, {"faab_balance": "0"}, {"number_of_moves": 31}, {"number_of_trades": "4"}, {"roster_adds": {"coverage_type": "week", "coverage_value": 17, "value": "0"}}, [], {"league_scoring_type": "head"}, [], [], {"has_draft_grade": 1, "draft_grade": "C", "draft_recap_url": "https://football.fantasysports.yahoo.com/2018/f1/209074/4/draftrecap"}, [], [], [], [], [], {"managers": [{"manager": {"manager_id": "4", "nickname": "Nark", "guid": "--hidden--", "image_url": "https://s.yimg.com/ag/images/default_user_profile_pic_64sq.jpg", "felo_score": "608", "felo_tier": "silver"}}]}], {"team_points": {"coverage_type": "season", "season": "2018", "total": "1169.94"}}, {"team_standings": {"rank": 9, "playoff_seed": "11", "outcome_totals": {"wins": "4", "losses": "9", "ties": 0, "percentage": ".308"}, "streak": {"type": "win", "value": "1"}, "points_for": "1169.94", "points_against": 1274.1599999999999}}]}, "9": {"team": [[{"team_key": "380.l.209074.t.7"}, {"team_id": "7"}, {"name": "Oh Say Quon You See"}, [], {"url": "https://football.fantasysports.yahoo.com/2018/f1/209074/7"}, {"team_logos": [{"team_logo": {"size": "large", "url": "https://yahoofantasysports-res.cloudinary.com/image/upload/t_s192sq/fantasy-logos/55812329142_b8f923.jpg"}}]}, {"previous_season_team_rank": 12}, [], {"waiver_priority": 1}, {"faab_balance": "72"}, {"number_of_moves": 11}, {"number_of_trades": "1"}, {"roster_adds": {"coverage_type": "week", "coverage_value": 17, "value": "0"}}, [], {"league_scoring_type": "head"}, [], [], {"has_draft_grade": 1, "draft_grade": "C+", "draft_recap_url": "https://football.fantasysports.yahoo.com/2018/f1/209074/7/draftrecap"}, [], [], [], [], [], {"managers": [{"manager": {"manager_id": "7", "nickname": "Nick", "guid": "--hidden--", "image_url": "https://s.yimg.com/ag/images/default_user_profile_pic_64sq.jpg", "felo_score": "566", "felo_tier": "bronze"}}]}], {"team_points": {"coverage_type": "season", "season": "2018", "total": "1204.64"}}, {"team_standings": {"rank": 10, "playoff_seed": "9", "outcome_totals": {"wins": "6", "losses": "7", "ties": 0, "percentage": ".462"}, "streak": {"type": "win", "value": "1"}, "points_for": "1204.64", "points_against": 1193.3000000000002}}]}, "10": {"team": [[{"team_key": "380.l.209074.t.6"}, {"team_id": "6"}, {"name": "MillDawg"}, [], {"url": "https://football.fantasysports.yahoo.com/2018/f1/209074/6"}, {"team_logos": [{"team_logo": {"size": "large", "url": "https://yahoofantasysports-res.cloudinary.com/image/upload/t_s192sq/fantasy-logos/25028243020_cda6f8ec5c.jpg"}}]}, {"previous_season_team_rank": 4}, [], {"waiver_priority": 11}, {"faab_balance": "6"}, {"number_of_moves": 21}, {"number_of_trades": 0}, {"roster_adds": {"coverage_type": "week", "coverage_value": 17, "value": "0"}}, [], {"league_scoring_type": "head"}, [], [], {"has_draft_grade": 1, "draft_grade": "B", "draft_recap_url": "https://football.fantasysports.yahoo.com/2018/f1/209074/6/draftrecap"}, [], [], [], [], [], {"managers": [{"manager": {"manager_id": "6", "nickname": "WW", "guid": "--hidden--", "image_url": "https://s.yimg.com/ag/images/default_user_profile_pic_64sq.jpg", "felo_score": "593", "felo_tier": "bronze"}}]}], {"team_points": {"coverage_type": "season", "season": "2018", "total": "1195.00"}}, {"team_standings": {"rank": 11, "playoff_seed": "10", "outcome_totals": {"wins": "4", "losses": "9", "ties": 0, "percentage": ".308"}, "streak": {"type": "loss", "value": "3"}, "points_for": "1195.00", "points_against": 1349.6599999999999}}]}, "11": {"team": [[{"team_key": "380.l.209074.t.8"}, {"team_id": "8"}, {"name": "Dalvin Cuck me good"}, {"is_owned_by_current_login": 1}, {"url": "https://football.fantasysports.yahoo.com/2018/f1/209074/8"}, {"team_logos": [{"team_logo": {"size": "large", "url": "https://yahoofantasysports-res.cloudinary.com/image/upload/t_s192sq/fantasy-logos/36839246771_8fc075.jpg"}}]}, {"previous_season_team_rank": 1}, [], {"waiver_priority": 10}, {"faab_balance": "0"}, {"number_of_moves": 18}, {"number_of_trades": 0}, {"roster_adds": {"coverage_type": "week", "coverage_value": 17, "value": "0"}}, [], {"league_scoring_type": "head"}, [], [], {"has_draft_grade": 1, "draft_grade": "C+", "draft_recap_url": "https://football.fantasysports.yahoo.com/2018/f1/209074/8/draftrecap"}, [], [], [], [], [], {"managers": [{"manager": {"manager_id": "8", "nickname": "BIGGUAP", "guid": "--hidden--", "is_current_login": "1", "image_url": "https://s.yimg.com/ag/images/default_user_profile_pic_64sq.jpg", "felo_score": "717", "felo_tier": "gold"}}]}], {"team_points": {"coverage_type": "season", "season": "2018", "total": "1086.20"}}, {"team_standings": {"rank": 12, "playoff_seed": "12", "outcome_totals": {"wins": "4", "losses": "9", "ties": 0, "percentage": ".308"}, "streak": {"type": "loss", "value": "1"}, "points_for": "1086.20", "points_against": 1271.7200000000003}}]}, "12": {"team": [[{"team_key": "380.l.209074.t.14"}, {"team_id": "14"}, {"name": "Trace for Heisman"}, [], {"url": "https://football.fantasysports.yahoo.com/2018/f1/209074/14"}, {"team_logos": [{"team_logo": {"size": "large", "url": "https://s.yimg.com/cv/apiv2/default/nfl/nfl_9.png"}}]}, {"previous_season_team_rank": 6}, [], {"waiver_priority": 7}, {"faab_balance": "0"}, {"number_of_moves": 20}, {"number_of_trades": 0}, {"roster_adds": {"coverage_type": "week", "coverage_value": 17, "value": "0"}}, [], {"league_scoring_type": "head"}, [], [], {"has_draft_grade": 1, "draft_grade": "D+", "draft_recap_url": "https://football.fantasysports.yahoo.com/2018/f1/209074/14/draftrecap"}, [], [], [], [], [], {"managers": [{"manager": {"manager_id": "14", "nickname": "Zack", "guid": "--hidden--", "image_url": "https://s.yimg.com/ag/images/default_user_profile_pic_64sq.jpg", "felo_score": "636", "felo_tier": "silver"}}]}], {"team_points": {"coverage_type": "season", "season": "2018", "total": "1059.88"}}, {"team_standings": {"rank": "13", "outcome_totals": {"wins": "3", "losses": "10", "ties": 0, "percentage": ".231"}, "streak": {"type": "loss", "value": "1"}, "points_for": "1059.88", "points_against": 1229.5}}]}, "13": {"team": [[{"team_key": "380.l.209074.t.11"}, {"team_id": "11"}, {"name": "Street Pharmacists"}, [], {"url": "https://football.fantasysports.yahoo.com/2018/f1/209074/11"}, {"team_logos": [{"team_logo": {"size": "large", "url": "https://yahoofantasysports-res.cloudinary.com/image/upload/t_s192sq/fantasy-logos/25299906525_b5a28436d3.jpg"}}]}, {"previous_season_team_rank": 14}, [], {"waiver_priority": 8}, {"faab_balance": "100"}, {"number_of_moves": 7}, {"number_of_trades": "1"}, {"roster_adds": {"coverage_type": "week", "coverage_value": 17, "value": "0"}}, [], {"league_scoring_type": "head"}, [], [], {"has_draft_grade": 1, "draft_grade": "B+", "draft_recap_url": "https://football.fantasysports.yahoo.com/2018/f1/209074/11/draftrecap"}, [], [], [], [], [], {"managers": [{"manager": {"manager_id": "11", "nickname": "Drew Patterson", "guid": "--hidden--", "image_url": "https://s.yimg.com/ag/images/default_user_profile_pic_64sq.jpg", "felo_score": "512", "felo_tier": "bronze"}}]}], {"team_points": {"coverage_type": "season", "season": "2018", "total": "1068.00"}}, {"team_standings": {"rank": "14", "outcome_totals": {"wins": "2", "losses": "11", "ties": 0, "percentage": ".154"}, "streak": {"type": "loss", "value": "7"}, "points_for": "1068.00", "points_against": 1352.5799999999997}}]}, "count": 14}}]}], "time": "116.34016036987ms", "copyright": "Certain Data by Sportradar, Stats Perform and Rotowire", "refresh_rate": "30"}}