{"fantasy_content": {"xml:lang": "en-US", "yahoo:uri": "/fantasy/v2/league/406.l.775456", "league": [{"league_key": "406.l.775456", "league_id": "775456", "name": "Sex Nodes", "url": "https://football.fantasysports.yahoo.com/2021/f1/775456", "recordbook_url": "https://football.fantasysports.yahoo.com/2021/f1/775456/recordbook?layout=webview&device=smartphone", "logo_url": false, "password": "", "draft_status": "predraft", "num_teams": 8, "edit_key": "17", "weekly_deadline": "", "roster_type": "week", "league_update_timestamp": null, "scoring_type": "head", "scoring_label": "H2H", "league_type": "private", "renew": "399_271338", "renewed": "414_522226", "felo_tier": "silver", "is_highscore": false, "is_guillotine": "0", "matchup_week": 17, "iris_group_chat_id": "", "short_invitation_url": "https://football.fantasysports.yahoo.com/2021/f1/775456/invitation?key=f67170de92fb9b3a&ikey=591739733f8fcf4c", "allow_add_to_dl_extra_pos": 1, "is_pro_league": "0", "is_cash_league": "0", "current_week": "17", "start_week": "1", "start_date": "2021-09-09", "end_week": "17", "end_date": "2022-01-03", "is_plus_league": "0", "game_code": "nfl", "season": "2021"}], "time": "22.175073623657ms", "copyright": "Certain Data by Sportradar, Stats Perform and Rotowire", "refresh_rate": "30"}}